simple_photo_gallery-1.5.7.dist-info/licenses/LICENSE
simplegallery/__init__.py
simplegallery/common.py
simplegallery/gallery_build.py
simplegallery/gallery_init.py
simplegallery/gallery_upload.py
simplegallery/media.py
simplegallery/bin/geckodriver
simplegallery/data/netlify/deploy.jinja
simplegallery/data/netlify/error.jinja
simplegallery/data/netlify/footer.jinja
simplegallery/data/netlify/header.jinja
simplegallery/data/netlify/index.jinja
simplegallery/data/public/css/default-skin.css
simplegallery/data/public/css/main.css
simplegallery/data/public/css/photoswipe.css
simplegallery/data/public/images/default-skin.png
simplegallery/data/public/images/default-skin.svg
simplegallery/data/public/images/preloader.gif
simplegallery/data/public/images/photos/.empty
simplegallery/data/public/images/thumbnails/.empty
simplegallery/data/public/js/main.js
simplegallery/data/public/js/photoswipe-ui-default.min.js
simplegallery/data/public/js/photoswipe.min.js
simplegallery/data/templates/gallery_macros.jinja
simplegallery/data/templates/index_template.jinja
simplegallery/logic/__init__.py
simplegallery/logic/base_gallery_logic.py
simplegallery/logic/gallery_logic.py
simplegallery/logic/variants/__init__.py
simplegallery/logic/variants/files_gallery_logic.py
simplegallery/logic/variants/google_gallery_logic.py
simplegallery/logic/variants/onedrive_gallery_logic.py
simplegallery/test/__init__.py
simplegallery/test/helpers.py
simplegallery/test/test_gallery_build.py
simplegallery/test/test_gallery_init.py
simplegallery/test/test_gallery_upload.py
simplegallery/test/logic/__init__.py
simplegallery/test/logic/test_gallery_logic.py
simplegallery/test/logic/variants/__init__.py
simplegallery/test/logic/variants/test_file_gallery_logic.py
simplegallery/test/logic/variants/test_google_gallery_logic.py
simplegallery/test/logic/variants/test_onedrive_gallery_logic.py
simplegallery/test/upload/__init__.py
simplegallery/test/upload/test_uploader_factory.py
simplegallery/test/upload/variants/__init__.py
simple_photo_gallery-1.5.7.dist-info/METADATA
simple_photo_gallery-1.5.7.dist-info/WHEEL
simple_photo_gallery-1.5.7.dist-info/entry_points.txt
simple_photo_gallery-1.5.7.dist-info/top_level.txt
simple_photo_gallery-1.5.7.dist-info/RECORD
