Metadata-Version: 2.4
Name: simple-photo-gallery
Version: 1.5.7
Summary: Pretty and simple HTML photo galleries you can host yourself.
Home-page: https://haltakov.net/simple-photo-gallery
Author: Vladimir Haltakov
Author-email: vladimir.haltakov@gmail.com
License: MIT
Project-URL: Documentation, https://haltakov.net/simple-photo-gallery
Keywords: photo video gallery self-hosted html
Classifier: Development Status :: 5 - Production/Stable
Classifier: License :: OSI Approved :: MIT License
Classifier: Programming Language :: Python :: 3
Requires-Python: >=3.6
License-File: LICENSE
Requires-Dist: opencv-python>=4.2.0.32
Requires-Dist: pillow>=7.0.0
Requires-Dist: jinja2>=2.10.3
Requires-Dist: selenium<4.3,>=3.141.0
Requires-Dist: requests>=2.22.0
Dynamic: author
Dynamic: author-email
Dynamic: classifier
Dynamic: description
Dynamic: description-content-type
Dynamic: home-page
Dynamic: keywords
Dynamic: license
Dynamic: license-file
Dynamic: project-url
Dynamic: requires-dist
Dynamic: requires-python
Dynamic: summary
